mssmViz/__init__.py
mssmViz/extract.py
mssmViz/plot.py
mssmViz/sim.py
mssmviz-0.1.49.dist-info/licenses/LICENSE
mssmviz-0.1.49.dist-info/METADATA
mssmviz-0.1.49.dist-info/WHEEL
mssmviz-0.1.49.dist-info/top_level.txt
mssmviz-0.1.49.dist-info/RECORD
