Metadata-Version: 2.4
Name: mssmViz
Version: 0.1.49
Summary: Plotting code to visualize models estimated with the mssm toolbox.
Author-email: Joshua Krause <jokra001@proton.me>
Classifier: Programming Language :: Python :: 3
Classifier: Operating System :: OS Independent
Requires-Python: >=3.10
License-File: LICENSE
Requires-Dist: numpy>=1.24.1
Requires-Dist: pandas>=1.5.3
Requires-Dist: scipy>=1.15.0
Requires-Dist: matplotlib>=3.8.2
Requires-Dist: mssm
Provides-Extra: dev
Requires-Dist: flake8; extra == "dev"
Requires-Dist: sphinx>=8.1.3; extra == "dev"
Requires-Dist: sphinx-rtd-theme>=3.0.2; extra == "dev"
Dynamic: license-file
